gitz/__init__.py
gitz/config.py
gitz/git/__init__.py
gitz/git/combine.py
gitz/git/delete.py
gitz/git/functions.py
gitz/git/guess_origin.py
gitz/git/mover.py
gitz/git/reference_branch.py
gitz/git/repo.py
gitz/git/root.py
gitz/git/save.py
gitz/program/__init__.py
gitz/program/env.py
gitz/program/log.py
gitz/program/parser.py
gitz/program/print_help.py
gitz/program/program.py
gitz/program/run_proc.py
gitz/program/runner.py
gitz/program/summaries.py
gitz-1.7.1.data/scripts/git-adjust
gitz-1.7.1.data/scripts/git-copy
gitz-1.7.1.data/scripts/git-delete
gitz-1.7.1.data/scripts/git-for-each
gitz-1.7.1.data/scripts/git-gitz
gitz-1.7.1.data/scripts/git-go
gitz-1.7.1.data/scripts/git-infer
gitz-1.7.1.data/scripts/git-multi-pick
gitz-1.7.1.data/scripts/git-new
gitz-1.7.1.data/scripts/git-permute
gitz-1.7.1.data/scripts/git-rename
gitz-1.7.1.data/scripts/git-rot
gitz-1.7.1.data/scripts/git-save
gitz-1.7.1.data/scripts/git-split
gitz-1.7.1.data/scripts/git-st
gitz-1.7.1.data/scripts/git-stripe
gitz-1.7.1.data/scripts/git-update
gitz-1.7.1.data/scripts/git-when
gitz-1.7.1.dist-info/LICENSE
gitz-1.7.1.dist-info/METADATA
gitz-1.7.1.dist-info/WHEEL
gitz-1.7.1.dist-info/entry_points.txt
gitz-1.7.1.dist-info/RECORD
