Metadata-Version: 2.1
Name: gitz
Version: 1.7.1
Summary: 🗜 Tiny useful git commands, some dangerous 🗜
Home-page: https://github.com/rec/gitz
Author: Tom Ritchford
Author-email: tom@swirly.com
Requires-Python: >=3.8
Classifier: Programming Language :: Python :: 3
Classifier: Programming Language :: Python :: 3.8
Classifier: Programming Language :: Python :: 3.9
Classifier: Programming Language :: Python :: 3.10
Classifier: Programming Language :: Python :: 3.11
Classifier: Programming Language :: Python :: 3.12
Requires-Dist: coverage (>=7.3.2,<8.0.0)
Project-URL: Repository, https://github.com/rec/gitz
